LICENSE
MANIFEST.in
README.md
setup.py
tests/__init__.py
tests/http_response_catcher.py
tests/test_helper.py
tests/controllers/__init__.py
tests/controllers/controller_test_base.py
tests/controllers/test_api_controller.py
ygrauzdokq/__init__.py
ygrauzdokq/api_helper.py
ygrauzdokq/configuration.py
ygrauzdokq/decorators.py
ygrauzdokq/ygrauzdokq_client.py
ygrauzdokq.egg-info/PKG-INFO
ygrauzdokq.egg-info/SOURCES.txt
ygrauzdokq.egg-info/dependency_links.txt
ygrauzdokq.egg-info/requires.txt
ygrauzdokq.egg-info/top_level.txt
ygrauzdokq/controllers/__init__.py
ygrauzdokq/controllers/api_controller.py
ygrauzdokq/controllers/base_controller.py
ygrauzdokq/exceptions/__init__.py
ygrauzdokq/exceptions/api_exception.py
ygrauzdokq/http/__init__.py
ygrauzdokq/http/http_call_back.py
ygrauzdokq/http/http_client.py
ygrauzdokq/http/http_context.py
ygrauzdokq/http/http_method_enum.py
ygrauzdokq/http/http_request.py
ygrauzdokq/http/http_response.py
ygrauzdokq/http/requests_client.py
ygrauzdokq/http/auth/__init__.py
ygrauzdokq/http/auth/basic_auth.py
ygrauzdokq/models/__init__.py
ygrauzdokq/models/suite_code_enum.py